binlist/__init__.py
binlist/iin/__init__.py
binlist/iin/bin.py
binlist/network/AmEx.py
binlist/network/ChinaTUnion.py
binlist/network/ChinaUnionPay.py
binlist/network/DinersClub.py
binlist/network/Discover.py
binlist/network/JCB.py
binlist/network/Maestro.py
binlist/network/MaestroUK.py
binlist/network/Mastercard.py
binlist/network/RuPay.py
binlist/network/Unknown.py
binlist/network/Visa.py
binlist/network/__init__.py
binlist/network/abstract.py
binlist-0.1.1.dist-info/AUTHORS.rst
binlist-0.1.1.dist-info/LICENSE
binlist-0.1.1.dist-info/METADATA
binlist-0.1.1.dist-info/WHEEL
binlist-0.1.1.dist-info/top_level.txt
binlist-0.1.1.dist-info/RECORD
