Metadata-Version: 2.1
Name: binlist
Version: 0.1.1
Summary: Python module for credit card BIN/IIN lookup.
Home-page: https://github.com/patdujour/python-binlist
Author: Patrick Zhang
Author-email: patdujour@gmail.com
License: MIT license
Keywords: binlist
Platform: UNKNOWN
Classifier: Development Status :: 2 - Pre-Alpha
Classifier: Intended Audience :: Developers
Classifier: License :: OSI Approved :: MIT License
Classifier: Natural Language :: English
Classifier: Programming Language :: Python :: 2
Classifier: Programming Language :: Python :: 2.7
Classifier: Programming Language :: Python :: 3
Classifier: Programming Language :: Python :: 3.4
Classifier: Programming Language :: Python :: 3.5
Classifier: Programming Language :: Python :: 3.6
Classifier: Programming Language :: Python :: 3.7
